version_mcp/__init__.py
version_mcp/server.py
version_mcp-0.1.0.dist-info/METADATA
version_mcp-0.1.0.dist-info/WHEEL
version_mcp-0.1.0.dist-info/entry_points.txt
version_mcp-0.1.0.dist-info/licenses/LICENSE
version_mcp-0.1.0.dist-info/RECORD
