Metadata-Version: 2.4
Name: version-mcp
Version: 0.1.0
Summary: MCP server for looking up package versions from pip, npm, and other package managers
License-Expression: MIT
License-File: LICENSE
Requires-Python: >=3.10
Requires-Dist: httpx>=0.28.0
Requires-Dist: mcp>=1.25.0
Provides-Extra: dev
Requires-Dist: pytest-asyncio>=1.0.0; extra == 'dev'
Requires-Dist: pytest>=9.0.0; extra == 'dev'
Requires-Dist: respx>=0.22.0; extra == 'dev'
Requires-Dist: ruff>=0.14.0; extra == 'dev'
